jivi/__init__.py
jivi/Curses/CURSES.py
jivi/Curses/__init__.py
jivi/callback/__init__.py
jivi/callback/callback.py
jivi/downloader/__init__.py
jivi/downloader/downloader.py
jivi/event/__init__.py
jivi/event/event.py
jivi/event/event_old.py
jivi/fs/__init__.py
jivi/fs/fs.py
jivi/menu/__init__.py
jivi/menu/menu.py
jivi/menu/addon/__init__.py
jivi/menu/addon/addon.py
jivi/menu/plugin/__init__.py
jivi/menu/plugin/plugin.py
jivi/packager/__init__.py
jivi/packager/configcreater.py
jivi/packager/packager.py
jivi/packager/packagerrun.py
jivi/tcpsock/__init__.py
jivi/tcpsock/tcpsock.py
jivi/test/__init__.py
jivi/test/download.py
jivi/test/fs.py
jivi/test/menu.py
jivi/test/menu_plugin.py
jivi/test/tester.py
jivi/test/uiinput.py
jivi/test/util.py
jivi/test/wrapper.py
jivi/tetris/__init__.py
jivi/tetris/view_helpers.rar.py
jivi/tetris/constant/__init__.py
jivi/tetris/constant/constant.py
jivi/tetris/controller/__init__.py
jivi/tetris/controller/controller.py
jivi/tetris/model/__init__.py
jivi/tetris/model/model.py
jivi/tetris/tetris_old/__init__.py
jivi/tetris/tetris_old/tetris.py
jivi/tetris/view/__init__.py
jivi/tetris/view/base.py
jivi/tetris/view/cur.py
jivi/tetris/view/electron.py
jivi/thread/__init__.py
jivi/thread/thread.py
jivi/uinput/UIInput.py
jivi/uinput/ValueGetter.py
jivi/uinput/__init__.py
jivi/uinput/inputparameters.py
jivi/uinput/models.py
jivi/uinput/Validator/__init__.py
jivi/uinput/Validator/validator.py
jivi/uinput/base/UIInput.py
jivi/uinput/base/ValueGetter.py
jivi/uinput/base/__init__.py
jivi/util/__init__.py
jivi/util/ideafailed.py
jivi/util/util.py
jivi/wrapper/__init__.py
jivi/wrapper/wrapper.py
jivi-0.0.24.dist-info/METADATA
jivi-0.0.24.dist-info/WHEEL
jivi-0.0.24.dist-info/top_level.txt
jivi-0.0.24.dist-info/RECORD
