Metadata-Version: 2.1
Name: jivi
Version: 0.0.24
Summary: Joris Vercleyen his personal library
Home-page: https://github.com/pypa/sampleproject
Author: Joris Vercleyen
Author-email: jorisvercleyen@gmail.com
License: UNKNOWN
Platform: UNKNOWN
Classifier: Programming Language :: Python :: 3
Classifier: License :: OSI Approved :: MIT License
Classifier: Operating System :: OS Independent
